pytoos/__init__.py
pytoos/creator.py
pytoos/editor.py
pytoos/remover.py
PyToOs-0.1.0.dist-info/METADATA
PyToOs-0.1.0.dist-info/WHEEL
PyToOs-0.1.0.dist-info/entry_points.txt
PyToOs-0.1.0.dist-info/top_level.txt
PyToOs-0.1.0.dist-info/RECORD
